Metadata-Version: 1.1
Name: marketify
Version: 0.2.1
Summary: A micro-library that pulls data from exchanges
Home-page: https://github.com/mfranco1/marketify
Author: Marcelino Franco
Author-email: mcfranco16@gmail.com
License: MIT
Download-URL: https://github.com/mfranco1/marketify/archive/v_021.tar.gz
Keywords: Trading,Market,Exchange,Websocket,Async
Platform: UNKNOWN
Classifier: Development Status :: 3 - Alpha
Classifier: Intended Audience :: Developers
Classifier: Topic :: Software Development :: Build Tools
Classifier: License :: OSI Approved :: MIT License
Classifier: Programming Language :: Python :: 3.6
Classifier: Programming Language :: Python :: 3.7
